par_clib/rr_arbiter.v
//----------------------------------------------------
// A four level, round-robin arbiter. 
// Nizar Dahir 2014
//----------------------------------------------------
module rr_arbiter (
  clk,    
  reset,    
  req0,   
  req1,   
  req2,   
  req3,   
  gnt0,   
  gnt1,   
  gnt2,   
  gnt3
);

// --------------Port Declaration----------------------- 
input           clk;    
input           reset;    

input           req0;   
input           req1;   
input           req2;   
input           req3;   
// input [1:0]     id; 
output  reg        gnt0;   
output  reg        gnt1;   
output  reg        gnt2;   
output  reg        gnt3;   

//--------------state register ----------------------- 
reg [1:0] state;

//--------------Code Starts Here----------------------- 
always @(posedge clk or posedge reset) begin
    if (reset) begin
	  
	  gnt0  <=  0;
	  gnt1  <=  0;
	  gnt2  <=  0;
	  gnt3  <=  0;
	  state <=  0;
	  
    end 
    else  begin 

//  shift priority only of a grant is given    
    if (gnt0) state <= 1;
    else if (gnt1) state <= 2;
    else if (gnt2) state <= 3;
    else if (gnt3) state <= 0;
    
      if (state==0)
	    begin 
		gnt0 <= req0;
		gnt1 <= req1 & !req0;
		gnt2 <= req2 & !req1 & !req0;
		gnt3 <= req3 & !req2 & !req1 & !req0;
// 		if (req0 | req1 | req2 | req3 ) state <= 1;
	     end
        else if (state==1)
	    begin
		gnt1 <= req1;
		gnt2 <= !req1 & req2;
		gnt3 <= !req2 & !req1 & req3;
		gnt0 <= !req3 & !req2 & !req1 & req0;
// 		if (req0 | req1 | req2 | req3 ) state <= 2;
	     end
        else if (state==2)
	    begin
		gnt2 <= req2;
		gnt3 <= !req2 & req3;
		gnt0 <= !req3 & !req2 & req0;
		gnt1 <= !req0 & !req3 & !req2 & req1;
// 		if (req0 | req1 | req2 | req3 )state <= 3;

	    end
        else if (state==3)
	    begin
		gnt3 <= req3;
		gnt0 <= !req3 & req0;
		gnt1 <= !req3 & !req0 & req1;
		gnt2 <= !req3 & !req0 & !req1 & req2;
// 		if (req0 | req1 | req2 | req3 ) state <= 0;
	    end
    end
end
    
endmodule

clib/rr_arbiter_tb.v

`include "rr_arbiter.v"
module top ();
reg             clk;    
reg             reset;    
reg             req3;   
reg             req2;   
reg             req1;   
reg             req0;   
wire            gnt3;   
wire            gnt2;   
wire            gnt1;   
wire            gnt0;  

// Clock generator
always #1 clk = ~clk;

initial begin
  $dumpfile ("arbiter.vcd");
  $dumpvars();
  clk = 0;
  reset = 1;
  req0 = 0;
  req1 = 0;
  req2 = 0;
  req3 = 0;
  #10 reset = 0;
  repeat (1) @ (posedge clk);
  req0 <= 1;
  req1 <= 1;
  req2 <= 1;
  req3 <= 1;
  repeat (1) @ (posedge clk);
  req0 <= 1;
  req1 <= 1;
  req2 <= 1;
  req3 <= 1;
  repeat (1) @ (posedge clk);
  req0 <= 1;
  req1 <= 1;
  req2 <= 1;
  req3 <= 1;
  repeat (1) @ (posedge clk);
  req0 <= 1;
  req1 <= 1;
  req2 <= 1;
  req3 <= 1;
  repeat (1) @ (posedge clk);
  req0 <= 1;
  req1 <= 1;
  req2 <= 1;
  req3 <= 1;
    
  /*repeat (1) @ (posedge clk);
  req0 <= 0;
  repeat (1) @ (posedge clk);
  req0 <= 1;
  req1 <= 1;
  repeat (1) @ (posedge clk);
  req2 <= 1;
  req1 <= 0;
  repeat (1) @ (posedge clk);
  req3 <= 1;
  req2 <= 0;
  repeat (1) @ (posedge clk);
  req3 <= 0;
  repeat (1) @ (posedge clk);
  req0 <= 0;
  repeat (1) @ (posedge clk); */
  #50 $finish;
end 

// Connect the DUT
rr_arbiter U (
 clk,    
 reset,    
 req3,   
 req2,   
 req1,   
 req0,   
 gnt3,   
 gnt2,   
 gnt1,   
 gnt0   
);

endmodule

clib/arbiter.vcd
$date
	Tue Oct 14 16:07:24 2014
$end
$version
	Icarus Verilog
$end
$timescale
	1s
$end
$scope module top $end
$var wire 1 ! gnt0 $end
$var wire 1 " gnt1 $end
$var wire 1 # gnt2 $end
$var wire 1 $ gnt3 $end
$var reg 1 % clk $end
$var reg 1 & req0 $end
$var reg 1 ' req1 $end
$var reg 1 ( req2 $end
$var reg 1 ) req3 $end
$var reg 1 * reset $end
$scope module U $end
$var wire 1 + clk $end
$var wire 1 , req0 $end
$var wire 1 - req1 $end
$var wire 1 . req2 $end
$var wire 1 / req3 $end
$var wire 1 0 reset $end
$var reg 1 1 gnt0 $end
$var reg 1 2 gnt1 $end
$var reg 1 3 gnt2 $end
$var reg 1 4 gnt3 $end
$var reg 2 5 state [1:0] $end
$upscope $end
$upscope $end
$enddefinitions $end
#0
$dumpvars
b0 5
04
03
02
01
10
0/
0.
0-
0,
0+
1*
0)
0(
0'
0&
0%
0$
0#
0"
0!
$end
#1
1%
1+
#2
0%
0+
#3
1%
1+
#4
0%
0+
#5
1%
1+
#6
0%
0+
#7
1%
1+
#8
0%
0+
#9
1%
1+
#10
0%
0+
0*
00
#11
1)
1,
1(
1-
1'
1.
1&
1/
1%
1+
#12
0%
0+
#13
b1 5
11
1$
1%
1+
#14
0%
0+
#15
b10 5
01
0$
12
1#
1%
1+
#16
0%
0+
#17
b11 5
02
0#
13
1"
1%
1+
#18
0%
0+
#19
b0 5
03
0"
14
1!
1%
1+
#20
0%
0+
#21
b1 5
04
0!
11
1$
1%
1+
#22
0%
0+
#23
b10 5
01
0$
12
1#
1%
1+
#24
0%
0+
#25
b11 5
02
0#
13
1"
1%
1+
#26
0%
0+
#27
b0 5
03
0"
14
1!
1%
1+
#28
0%
0+
#29
b1 5
04
0!
11
1$
1%
1+
#30
0%
0+
#31
b10 5
01
0$
12
1#
1%
1+
#32
0%
0+
#33
b11 5
02
0#
13
1"
1%
1+
#34
0%
0+
#35
b0 5
03
0"
14
1!
1%
1+
#36
0%
0+
#37
b1 5
04
0!
11
1$
1%
1+
#38
0%
0+
#39
b10 5
01
0$
12
1#
1%
1+
#40
0%
0+
#41
b11 5
02
0#
13
1"
1%
1+
#42
0%
0+
#43
b0 5
03
0"
14
1!
1%
1+
#44
0%
0+
#45
b1 5
04
0!
11
1$
1%
1+
#46
0%
0+
#47
b10 5
01
0$
12
1#
1%
1+
#48
0%
0+
#49
b11 5
02
0#
13
1"
1%
1+
#50
0%
0+
#51
b0 5
03
0"
14
1!
1%
1+
#52
0%
0+
#53
b1 5
04
0!
11
1$
1%
1+
#54
0%
0+
#55
b10 5
01
0$
12
1#
1%
1+
#56
0%
0+
#57
b11 5
02
0#
13
1"
1%
1+
#58
0%
0+
#59
b0 5
03
0"
14
1!
1%
1+
#60
0%
0+
#61
b1 5
04
0!
11
1$
1%
1+
#62
0%
0+
#63
b10 5
01
0$
12
1#
1%
1+
#64
0%
0+
#65
b11 5
02
0#
13
1"
1%
1+
#66
0%
0+
#67
b0 5
03
0"
14
1!
1%
1+
#68
0%
0+
#69
b1 5
04
0!
11
1$
1%
1+
