par_clib/dclkfifo.v

`define DCLK_FIFO_DEPTH_LOG2 3

`define DCLK_FIFO_DEPTH (1<<`DCLK_FIFO_DEPTH_LOG2)



module dclkfifo(rclk, wclkp, reset, full, empty, item_in, item_out, write, read);

	parameter routerid=-1;
	parameter DCLK_FIFO_DSIZE = 4;

	input rclk, wclkp, reset, write, read;
	
	output full, empty;
	
	reg [DCLK_FIFO_DSIZE -1:0] mem [`DCLK_FIFO_DEPTH-1:0];
	
	reg [`DCLK_FIFO_DEPTH_LOG2-1:0] read_ptr;
	
	reg [`DCLK_FIFO_DEPTH_LOG2-1:0] write_ptr;
	
	reg [`DCLK_FIFO_DEPTH_LOG2:0] count;
	
	wire [`DCLK_FIFO_DEPTH_LOG2-1:0] read_ptr_p1; assign read_ptr_p1 = read_ptr + 1;
	
	wire [`DCLK_FIFO_DEPTH_LOG2-1:0] write_ptr_p1; assign write_ptr_p1 = write_ptr + 1;
	
	input [DCLK_FIFO_DSIZE -1:0] item_in;
	
	output [DCLK_FIFO_DSIZE -1:0] item_out;
	
// 	reg full, empty;
	
	integer i;

	assign wclk = !wclkp;  // for write clock 

	
	assign full= (count == `DCLK_FIFO_DEPTH - 1);
	
	assign empty= (count == 0);
	
// 	writing clock
	always @(posedge wclk) begin
	
		if (reset) begin
		
			write_ptr <= 0;
			
			read_ptr <= 0;
			
			count <= 0;			

		end 
		else begin 

		    if (write & !full) begin
		    
			mem [write_ptr] <= item_in;
			    
			write_ptr <= write_ptr_p1;
			    
			count <= count + 1;
			    
// 			if (!read) count <= count+1;

			if (routerid > -1) $display("router %d fifo push : %d", routerid, item_in);

		    end
		
		end
	
	end
	
	// reading clock
	always @(posedge rclk) begin
	
		if (reset) begin
			
			write_ptr <= 0;
		
			read_ptr <= 0;
			
			count <= 0;			

		end else begin
		
			if (read & !empty) begin
				
				read_ptr <= read_ptr_p1;

 				count <= count - 1;

// 				if (!write) count <= count-1;
				
				if (routerid > -1) $display("router %d fifo pop : %d", routerid, item_out);
			
			end 

		end
	
	end
	
	assign item_out = mem [read_ptr];
	

endmodule

par_clib/dclkfifo_tb.v

`include "dclkfifo.v"
module top ();

wire             rclk;    
wire            wclk;    
wire            reset;    
wire            full;   
wire            empty;   
wire 		write;
wire 		read;

wire   [3:0]    item_in;   
wire   [3:0]    item_out;  


// Connect the DUT
  generator #(2, 4)  g0(rclk, wclk, reset, item_in, write, read);
  
  dclkfifo dclkfifo0 (rclk, wclk, reset, full, empty, item_in, item_out, write, read);
  
endmodule


module generator(rclk, wclk, reset, item_in, write, read);
	output  rclk, wclk,  reset, write, read;
	output  [3:0] item_in;
	
	reg rclk, wclk,  reset, write, read;
	reg [3:0] item_in;
	
	initial 
	begin 
	
		rclk = 0;
		
		wclk = 1;
		
		item_in = 0;
		
		write = 0;
		
		read = 0; 
		
		#0 reset = 1; 
		
		#8 reset = 0;

	end 
	
	always 
	begin
		#2 rclk = !rclk;
		
	end
	
	always 
	begin
		#1 wclk = !wclk;
		#1 wclk =  wclk;
		#1 wclk = !wclk;
		#1 wclk =  wclk;
		
	end
	
	initial $display("Start of simulation ...");
	
	initial
        begin
        
		$dumpfile("fifodump.vcd");
	    
		$dumpvars();
	end

	
	initial     
	begin
// 		$display("Sending data ...");
		
		#11 
		item_in = 1;
		write = 1;
		
		#3
		read = 1;
		
		#1 
		item_in = 2;

		#3
		read = 0;
		
		#1
		item_in = 3;
		
		#3
		read = 1;
		
		#1
		item_in = 4;
		
		#3
		read = 0;

		#1
		item_in = 5;

// 		#4
// 		write = 0;

		#3
		read = 1;
		
		#4
		read = 0;

      
		#28  $finish;
	end



endmodule

par_clib/fifodump.vcd
$date
	Fri Oct 24 16:42:41 2014
$end
$version
	Icarus Verilog
$end
$timescale
	1s
$end
$scope module top $end
$var wire 1 ! empty $end
$var wire 1 " full $end
$var wire 4 # item_in [3:0] $end
$var wire 4 $ item_out [3:0] $end
$var wire 1 % rclk $end
$var wire 1 & read $end
$var wire 1 ' reset $end
$var wire 1 ( wclk $end
$var wire 1 ) write $end
$scope module g0 $end
$var reg 4 * item_in [3:0] $end
$var reg 1 + rclk $end
$var reg 1 , read $end
$var reg 1 - reset $end
$var reg 1 . wclk $end
$var reg 1 / write $end
$upscope $end
$scope module dclkfifo0 $end
$var wire 1 ! empty $end
$var wire 1 " full $end
$var wire 4 0 item_in [3:0] $end
$var wire 4 1 item_out [3:0] $end
$var wire 1 % rclk $end
$var wire 1 & read $end
$var wire 3 2 read_ptr_p1 [2:0] $end
$var wire 1 ' reset $end
$var wire 1 3 wclk $end
$var wire 1 ( wclkp $end
$var wire 1 ) write $end
$var wire 3 4 write_ptr_p1 [2:0] $end
$var reg 4 5 count [3:0] $end
$var reg 3 6 read_ptr [2:0] $end
$var reg 3 7 write_ptr [2:0] $end
$upscope $end
$upscope $end
$enddefinitions $end
#0
$dumpvars
bx 7
bx 6
bx 5
bx 4
03
bx 2
bx 1
b0 0
0/
1.
1-
0,
0+
b0 *
0)
1(
1'
0&
0%
bx $
b0 #
x"
x!
$end
#1
b1 2
b1 4
b0 5
0"
1!
b0 6
b0 7
0.
13
0(
#2
1+
1%
#3
1.
03
1(
#4
0+
0%
#5
0.
13
0(
#6
1+
1%
#7
1.
03
1(
#8
0+
0%
0-
0'
#9
0.
13
0(
#10
1+
1%
#11
1.
03
1(
1/
1)
b1 *
b1 #
b1 0
#12
0+
0%
#13
b10 4
b1 5
0!
b1 7
b1 $
b1 1
0.
13
0(
#14
b10 2
b0 5
1!
b1 6
bx $
bx 1
1+
1%
1,
1&
#15
1.
03
1(
b10 *
b10 #
b10 0
#16
0+
0%
#17
b11 4
b1 5
0!
b10 7
b10 $
b10 1
0.
13
0(
#18
1+
1%
0,
0&
#19
1.
03
1(
#20
0+
0%
#21
b100 4
b10 5
b11 7
0.
13
0(
#22
1+
1%
b11 *
b11 #
b11 0
#23
1.
03
1(
#24
0+
0%
#25
b101 4
b11 5
b100 7
0.
13
0(
#26
1+
1%
b100 *
b100 #
b100 0
#27
1.
03
1(
#28
0+
0%
#29
b110 4
b100 5
b101 7
0.
13
0(
#30
1+
1%
b101 *
b101 #
b101 0
#31
1.
03
1(
#32
0+
0%
#33
b111 4
b101 5
b110 7
0.
13
0(
#34
1+
1%
0/
0)
#35
1.
03
1(
#36
0+
0%
#37
0.
13
0(
1,
1&
#38
b11 2
b100 5
b10 6
1+
1%
#39
1.
03
1(
#40
0+
0%
#41
0.
13
0(
#42
b100 2
b11 5
b11 6
b11 $
b11 1
1+
1%
#43
1.
03
1(
#44
0+
0%
#45
0.
13
0(
#46
b101 2
b10 5
b100 6
b100 $
b100 1
1+
1%
#47
1.
03
1(
#48
0+
0%
#49
0.
13
0(
#50
b110 2
b1 5
b101 6
b101 $
b101 1
1+
1%
#51
1.
03
1(
#52
0+
0%
#53
0.
13
0(
#54
b111 2
b0 5
1!
b110 6
bx $
bx 1
1+
1%
